raw_packet/__init__.py
raw_packet/Scanners/__init__.py
raw_packet/Scanners/arp_scanner.py
raw_packet/Scanners/icmpv6_router_search.py
raw_packet/Scanners/icmpv6_scanner.py
raw_packet/Scanners/nmap_scanner.py
raw_packet/Scripts/__init__.py
raw_packet/Scripts/ARP/__init__.py
raw_packet/Scripts/ARP/arp_fuzz.py
raw_packet/Scripts/ARP/arp_scan.py
raw_packet/Scripts/ARP/arp_spoof.py
raw_packet/Scripts/Apple/__init__.py
raw_packet/Scripts/Apple/apple_arp_dos.py
raw_packet/Scripts/Apple/apple_dhcp_server.py
raw_packet/Scripts/Apple/apple_mitm.py
raw_packet/Scripts/Binary/__init__.py
raw_packet/Scripts/Binary/dnsmasploit.py
raw_packet/Scripts/DHCPv4/__init__.py
raw_packet/Scripts/DHCPv4/dhcp_fuzz.py
raw_packet/Scripts/DHCPv4/dhcp_starvation.py
raw_packet/Scripts/DHCPv4/dhcpv4_server.py
raw_packet/Scripts/DHCPv6/__init__.py
raw_packet/Scripts/DHCPv6/dhcpv6_server.py
raw_packet/Scripts/DNS/__init__.py
raw_packet/Scripts/DNS/dns_resolver.py
raw_packet/Scripts/DNS/dns_server.py
raw_packet/Scripts/ICMPv4/__init__.py
raw_packet/Scripts/ICMPv4/icmpv4_redirect.py
raw_packet/Scripts/IPv6/__init__.py
raw_packet/Scripts/IPv6/ipv6_scan.py
raw_packet/Scripts/IPv6/ipv6_spoof.py
raw_packet/Scripts/NCC/__init__.py
raw_packet/Scripts/NCC/ncc.py
raw_packet/Scripts/NSC/__init__.py
raw_packet/Scripts/NSC/nsc.py
raw_packet/Scripts/Others/__init__.py
raw_packet/Scripts/Others/examples.py
raw_packet/Scripts/Others/sniff_test.py
raw_packet/Scripts/Others/time_test.py
raw_packet/Scripts/Phishing/__init__.py
raw_packet/Scripts/Phishing/phishing.py
raw_packet/Scripts/WiFi/__init__.py
raw_packet/Scripts/WiFi/wat.py
raw_packet/Senders/__init__.py
raw_packet/Senders/dns_resolver.py
raw_packet/Senders/send_arp_packets.py
raw_packet/Senders/send_dhcp_discover.py
raw_packet/Senders/send_dhcp_release.py
raw_packet/Senders/send_dns_query.py
raw_packet/Senders/send_icmpv6_ra_packets.py
raw_packet/Senders/send_icmpv6_rs_packets.py
raw_packet/Senders/send_tcp_packets.py
raw_packet/Servers/__init__.py
raw_packet-0.2.1.dist-info/METADATA
raw_packet-0.2.1.dist-info/WHEEL
raw_packet-0.2.1.dist-info/entry_points.txt
raw_packet-0.2.1.dist-info/top_level.txt
raw_packet-0.2.1.dist-info/RECORD
