Metadata-Version: 2.1
Name: raw-packet
Version: 0.2.1
Summary: Raw-packet Project
Home-page: https://raw-packet.github.io/
Author: Vladimir Ivanov
Author-email: ivanov.vladimir.mail@gmail.com
License: UNKNOWN
Platform: UNKNOWN
Classifier: Development Status :: 4 - Beta
Classifier: Environment :: Console
Classifier: Environment :: Console :: Curses
Classifier: Environment :: MacOS X
Classifier: Intended Audience :: Education
Classifier: License :: Free For Educational Use
Classifier: License :: OSI Approved :: MIT License
Classifier: Natural Language :: English
Classifier: Operating System :: MacOS
Classifier: Operating System :: POSIX :: Linux
Classifier: Programming Language :: Python :: 3 :: Only
Classifier: Programming Language :: Python :: 3.6
Classifier: Programming Language :: Python :: 3.7
Classifier: Programming Language :: Python :: 3.8
Classifier: Programming Language :: Python :: 3.9
Classifier: Topic :: Education
Classifier: Topic :: Security
Requires-Python: >=3.6
Requires-Dist: ipaddress
Requires-Dist: netaddr
Requires-Dist: scapy
Requires-Dist: psutil
Requires-Dist: prettytable
Requires-Dist: distro
Requires-Dist: xmltodict
Requires-Dist: paramiko
Requires-Dist: npyscreen
Requires-Dist: pycryptodomex
Requires-Dist: getmac
Requires-Dist: colorama
Requires-Dist: requests
Requires-Dist: user-agents
Requires-Dist: netifaces ; sys_platform=="darwin"
Requires-Dist: netifaces ; sys_platform=="linux"
